coininfo_brunowv/__init__.py
coininfo_brunowv/info.py
coininfo_brunowv-0.1.dist-info/METADATA
coininfo_brunowv-0.1.dist-info/WHEEL
coininfo_brunowv-0.1.dist-info/top_level.txt
coininfo_brunowv-0.1.dist-info/RECORD
